README.rst
setup.py
CModules/LanczosFunctions.c
CModules/LanczosFunctions.h
CModules/odd_corr_module.c
Modules/Dynamical.py
Modules/DynamicalLanczos.py
Modules/Parallel.py
Modules/Perturbations.py
Modules/StaticHessian.py
Modules/Tools.py
Modules/__init__.py
Modules/tdscha_core.jl
scripts/plot_hessian_convergence.py
scripts/tdscha-convergence-analysis.py
scripts/tdscha-output2abc.py
scripts/tdscha-plot.py
tdscha.egg-info/PKG-INFO
tdscha.egg-info/SOURCES.txt
tdscha.egg-info/dependency_links.txt
tdscha.egg-info/requires.txt
tdscha.egg-info/top_level.txt