Metadata-Version: 2.1
Name: tdscha
Version: 1.4.0
Summary: Time Dependent Self Consistent Harmonic Approximation
Home-page: https://github.com/SSCHAcode/tdscha
Author: Lorenzo Monacelli
License: GPLv3
